openai_gpt_image_1/__init__.py
openai_gpt_image_1/resources/__init__.py
openai_gpt_image_1/tools/__init__.py
openai_gpt_image_1/tools/basic_tools.py
openai_gpt_image_1_mcp-0.1.3.dist-info/licenses/LICENSE
openai_gpt_image_1_server/__init__.py
openai_gpt_image_1_mcp-0.1.3.dist-info/METADATA
openai_gpt_image_1_mcp-0.1.3.dist-info/WHEEL
openai_gpt_image_1_mcp-0.1.3.dist-info/entry_points.txt
openai_gpt_image_1_mcp-0.1.3.dist-info/top_level.txt
openai_gpt_image_1_mcp-0.1.3.dist-info/RECORD
