Metadata-Version: 2.4
Name: openai-gpt-image-1-mcp
Version: 0.1.3
Summary: OpenAI Image Generation MCP Server for AI assistant access to OpenAI's image generation capabilities
Author-email: DevRico003 <devrico003@gmail.com>
License-Expression: MIT
Project-URL: Homepage, https://github.com/DevRico003/openai-gpt-image-1-mcp
Project-URL: Bug Tracker, https://github.com/DevRico003/openai-gpt-image-1-mcp/issues
Project-URL: Source Code, https://github.com/DevRico003/openai-gpt-image-1-mcp
Keywords: openai,image,generation,gpt-image-1,api,mcp,llm,ai,assistant
Classifier: Development Status :: 4 - Beta
Classifier: Intended Audience :: Developers
Classifier: Programming Language :: Python :: 3
Classifier: Programming Language :: Python :: 3.8
Classifier: Programming Language :: Python :: 3.9
Classifier: Programming Language :: Python :: 3.10
Classifier: Programming Language :: Python :: 3.11
Classifier: Programming Language :: Python :: 3.12
Classifier: Topic :: Software Development :: Libraries :: Python Modules
Classifier: Topic :: Internet :: WWW/HTTP
Requires-Python: >=3.10
License-File: LICENSE
Requires-Dist: httpx>=0.27.0
Requires-Dist: openai>=1.0.0
Requires-Dist: mcp>=0.4.0
Provides-Extra: dev
Requires-Dist: pytest>=7.0.0; extra == "dev"
Requires-Dist: pytest-asyncio>=0.20.0; extra == "dev"
Dynamic: license-file
